hello_sethlee/__init__.py
hello_sethlee/main.py
hello_sethlee-0.7.0.dist-info/METADATA
hello_sethlee-0.7.0.dist-info/WHEEL
hello_sethlee-0.7.0.dist-info/entry_points.txt
hello_sethlee-0.7.0.dist-info/top_level.txt
hello_sethlee-0.7.0.dist-info/RECORD
