Metadata-Version: 2.1
Name: hello_sethlee
Version: 0.7.0
